
{"items":[{"name":"ASE_Assignment_Toms_Project","href":"ASE_Assignment_Toms_Project.html","topicHref":"ASE_Assignment_Toms_Project.html","topicUid":"ASE_Assignment_Toms_Project","items":[{"name":"AppCanvas","href":"ASE_Assignment_Toms_Project.AppCanvas.html","topicHref":"ASE_Assignment_Toms_Project.AppCanvas.html","topicUid":"ASE_Assignment_Toms_Project.AppCanvas"},{"name":"AppCommandFactory","href":"ASE_Assignment_Toms_Project.AppCommandFactory.html","topicHref":"ASE_Assignment_Toms_Project.AppCommandFactory.html","topicUid":"ASE_Assignment_Toms_Project.AppCommandFactory"},{"name":"Form1","href":"ASE_Assignment_Toms_Project.Form1.html","topicHref":"ASE_Assignment_Toms_Project.Form1.html","topicUid":"ASE_Assignment_Toms_Project.Form1"}]},{"name":"AppUnitTest","href":"AppUnitTest.html","topicHref":"AppUnitTest.html","topicUid":"AppUnitTest","items":[{"name":"UnitTest1","href":"AppUnitTest.UnitTest1.html","topicHref":"AppUnitTest.UnitTest1.html","topicUid":"AppUnitTest.UnitTest1"}]}],"memberLayout":"SamePage","pdf":true}
